scytale/__init__.py
scytale/algorithm.py
scytale/crypto/__init__.py
scytale/crypto/elgamal_pkc.py
scytale/crypto/goldmicali.py
scytale/crypto/pkc_template.py
scytale/crypto/rsa.py
scytale/crypto/vigenere.py
scytale/ecurve/__init__.py
scytale/ecurve/elliptic_curve.py
scytale/factor/__init__.py
scytale/factor/main.py
scytale/lattice/__init__.py
scytale/lattice/main.py
scytale-0.3.6a0.dist-info/LICENSE.txt
scytale-0.3.6a0.dist-info/METADATA
scytale-0.3.6a0.dist-info/WHEEL
scytale-0.3.6a0.dist-info/top_level.txt
scytale-0.3.6a0.dist-info/RECORD
