Metadata-Version: 2.1
Name: scytale
Version: 0.3.6a0
Summary: Algorithms in Crytography and Number Theory
Home-page: https://github.com/MarcoYLyu/scytale
Author: Yi Lyu
Author-email: marcolyu@g.ucla.edu
License: Apache License 2.0
Download-URL: https://github.com/MarcoYLyu/scytale/releases/tag/v0.3.6-alpha
Keywords: cryptography,math116
Platform: UNKNOWN
Classifier: Development Status :: 3 - Alpha
Classifier: Intended Audience :: Developers
Classifier: Topic :: Software Development :: Build Tools
Classifier: Programming Language :: Python :: 3
Classifier: Programming Language :: Python :: 3.4
Classifier: Programming Language :: Python :: 3.5
Classifier: Programming Language :: Python :: 3.6
Requires-Dist: numpy
